{
  "template": "git@github.com:neptunes5thmoon/cookiecrumbles.git",
  "commit": "e3f64f045bc80438e49c92cd3ea5b600cb9c9c14",
  "checkout": null,
  "context": {
    "cookiecutter": {
      "project_name": "em+label_generation",
      "experiment_name": "exp09",
      "project_slug": "exp09",
      "author": "Larissa Heinrich",
      "author_email": "heinrichl@janelia.hhmi.org",
      "parent_repo": "https://github.com/saalfeldlab/diffusion-experiments",
      "experiment_description": "Use all data",
      "my_repo_deps": {
        "repo": [
          "denoising-diffusion-pytorch@git+ssh://git@github.com/neptunes5thmoon/denoising-diffusion-pytorch.git",
          "labelcomposer@git+ssh://git@github.com/saalfeldlab/labelcomposer.git",
          "cellmap-utils-kit@git+ssh://git@github.com/saalfeldlab/cellmap-utils-kit.git"
        ],
        "branch": [
          "mymain",
          "main",
          "main"
        ],
        "use_latest_commit": [
          true,
          true,
          true
        ]
      },
      "_template": "git@github.com:neptunes5thmoon/cookiecrumbles.git"
    }
  },
  "directory": "diffusion-experiments"
}
